{
  "concepts": {
    "ai_organization": {
      "type": "system",
      "components": ["PRESIDENT", "BOSS1", "WORKER1", "WORKER2", "WORKER3"],
      "relationships": ["hierarchy", "collaboration", "automation"],
      "capabilities": ["task_distribution", "parallel_processing", "autonomous_operation"]
    },
    "continuous_improvement": {
      "type": "methodology",
      "phases": ["Phase1", "Phase2", "Phase3"],
      "techniques": ["error_learning", "system_optimization", "knowledge_accumulation"],
      "outcomes": ["efficiency_increase", "capability_expansion", "autonomous_growth"]
    },
    "problem_solving": {
      "type": "process",
      "approaches": ["analytical", "creative", "collaborative", "systematic"],
      "tools": ["decomposition", "pattern_recognition", "synthesis", "evaluation"],
      "strategies": ["divide_and_conquer", "iterative_refinement", "parallel_exploration"]
    }
  },
  "relationships": {
    "synergies": [
      {"from": "ai_organization", "to": "continuous_improvement", "type": "enables"},
      {"from": "continuous_improvement", "to": "problem_solving", "type": "enhances"},
      {"from": "problem_solving", "to": "ai_organization", "type": "strengthens"}
    ]
  },
  "learning_patterns": {
    "successful_strategies": [],
    "failed_approaches": [],
    "emerging_capabilities": []
  },
  "evolution_metrics": {
    "complexity_handling": 0,
    "creative_solutions": 0,
    "autonomous_decisions": 0,
    "knowledge_synthesis": 0
  }
}
